{"Items":[{"itemName":"large Pizza","itemId":"1002","price":14,"quantity":1},{"itemName":"Medium Pizza","itemId":"1008","price":8,"quantity":1},{"itemName":"Small Pizza","itemId":"1001","price":14,"quantity":1},{"itemName":"Garlic Bread","itemId":"1005","price":8,"quantity":1},{"itemName":"Large Pizza","itemId":"1001","price":14,"quantity":2},{"itemName":"Browny","itemId":"1005","price":8,"quantity":5},{"itemName":"Large Pizza","itemId":"1001","price":10,"quantity":2},{"itemName":"Pizza","itemId":"1001","price":24,"quantity":2}]}